README.rst
setup.py
basebot/__init__.py
basebot/bot.py
basebot/configloader.py
basebot/core.py
basebot.egg-info/PKG-INFO
basebot.egg-info/SOURCES.txt
basebot.egg-info/dependency_links.txt
basebot.egg-info/entry_points.txt
basebot.egg-info/requires.txt
basebot.egg-info/top_level.txt