Metadata-Version: 1.1
Name: basebot
Version: 1.0.8
Summary: a base IRC bot extensible with plugins
Home-page: https://github.com/clearskies/basebot
Author: Anthony Nguyen
Author-email: anknguyen@gmail.com
License: MIT
Platform: UNKNOWN
Classifier: Intended Audience :: Developers
Classifier: License :: OSI Approved :: MIT License
Classifier: Natural Language :: English
Classifier: Operating System :: Unix
Classifier: Programming Language :: Python :: 3
Classifier: Topic :: Communications :: Chat :: Internet Relay Chat
